django_editorjs_field/__init__.py
django_editorjs_field/field.py
django_editorjs_field/static/django_editorjs_field/css/typebase.css
django_editorjs_field/static/django_editorjs_field/js/editor.js
django_editorjs_field/templates/django_editorjs_field/tools/p.html
django_editorjs_field/templates/django_editorjs_field/widget.html
django_editorjs_field/templatetags/__init__.py
django_editorjs_field/templatetags/editorjs.py
django_editorjs_field/tool.py
django_editorjs_field/utils.py
django_editorjs_field/widget.py
django_editorjs_field_next-0.1.2.dist-info/METADATA
django_editorjs_field_next-0.1.2.dist-info/LICENSE
django_editorjs_field_next-0.1.2.dist-info/WHEEL
django_editorjs_field_next-0.1.2.dist-info/RECORD
