Metadata-Version: 2.1
Name: django-editorjs-field-next
Version: 0.1.2
Summary: An EditorJS Field with dependency injection of tools support for Django >4.*
Home-page: https://github.com/eijawa/django-editorjs-field
License: MIT
Author: Evgeniy Gribanov
Author-email: evgeniy.therabbit@gmail.com
Requires-Python: >=3.11,<4.0
Classifier: License :: OSI Approved :: MIT License
Classifier: Programming Language :: Python :: 3
Classifier: Programming Language :: Python :: 3.11
Requires-Dist: django (>=4.1.3,<5.0.0)
Project-URL: Repository, https://github.com/eijawa/django-editorjs-field
